propel_client/__init__.py
propel_client/cli.py
propel_client/constants.py
propel_client/cred_storage.py
propel_client/propel.py
propel_client/utils.py
propel_client-0.0.19.dist-info/METADATA
propel_client-0.0.19.dist-info/WHEEL
propel_client-0.0.19.dist-info/entry_points.txt
propel_client-0.0.19.dist-info/licenses/AUTHORS.md
propel_client-0.0.19.dist-info/licenses/LICENSE
propel_client-0.0.19.dist-info/RECORD
