Metadata-Version: 2.4
Name: propel-client
Version: 0.0.19
Summary: Propel service client
License-File: AUTHORS.md
License-File: LICENSE
Author: Yuri Turchenkov
Author-email: yuri.turchenkov@valory.xyz
Requires-Python: >=3.10,<4.0
Classifier: Programming Language :: Python :: 3
Classifier: Programming Language :: Python :: 3.10
Classifier: Programming Language :: Python :: 3.11
Classifier: Programming Language :: Python :: 3.12
Classifier: Programming Language :: Python :: 3.13
Classifier: Programming Language :: Python :: 3.14
Requires-Dist: click (==8.1.8)
Requires-Dist: multiaddr (==0.0.12)
Requires-Dist: open-autonomy (==v0.19.7)
Requires-Dist: pymultihash (==0.8.2)
Requires-Dist: requests
